{
    "winner": "dire", 
    "factions": {
        "radiant": {
            "heroes": [
                {
                    "dn": "1", 
                    "gpm": "237", 
                    "lane": "Top (Off)", 
                    "hero_name": "/heroes/earthshaker", 
                    "player_name": "EHOME.old el...", 
                    "gold": "6.9k", 
                    "kills": "1", 
                    "level": "11", 
                    "deaths": "6", 
                    "kda": "0.7", 
                    "lh": "79", 
                    "hh": "-", 
                    "assists": "3", 
                    "player_id": "/players/134276083", 
                    "td": "-", 
                    "xpm": "217", 
                    "hd": "2.3k"
                }, 
                {
                    "dn": "3", 
                    "gpm": "203", 
                    "lane": "Bottom (Safe)", 
                    "hero_name": "/heroes/vengeful-spirit", 
                    "player_name": "EHOME.LaNm", 
                    "gold": "5.9k", 
                    "kills": "1", 
                    "level": "10", 
                    "deaths": "3", 
                    "kda": "1.3", 
                    "lh": "50", 
                    "hh": "773", 
                    "assists": "3", 
                    "player_id": "/players/89423756", 
                    "td": "206", 
                    "xpm": "198", 
                    "hd": "2.7k"
                }, 
                {
                    "dn": "5", 
                    "gpm": "389", 
                    "lane": "Middle", 
                    "hero_name": "/heroes/doom", 
                    "player_name": "EHOME.old ch...", 
                    "gold": "11.3k", 
                    "kills": "4", 
                    "level": "13", 
                    "deaths": "6", 
                    "kda": "0.8", 
                    "lh": "135", 
                    "hh": "-", 
                    "assists": "1", 
                    "player_id": "/players/135878232", 
                    "td": "210", 
                    "xpm": "326", 
                    "hd": "7.2k"
                }, 
                {
                    "dn": "42", 
                    "gpm": "513", 
                    "lane": "Bottom (Safe)", 
                    "hero_name": "/heroes/queen-of-pain", 
                    "player_name": "VG.CTY", 
                    "gold": "14.8k", 
                    "kills": "2", 
                    "level": "17", 
                    "deaths": "1", 
                    "kda": "5.0", 
                    "lh": "232", 
                    "hh": "-", 
                    "assists": "3", 
                    "player_id": "/players/108376607", 
                    "td": "1.2k", 
                    "xpm": "539", 
                    "hd": "6.7k"
                }, 
                {
                    "dn": "-", 
                    "gpm": "141", 
                    "lane": "Middle", 
                    "hero_name": "/heroes/earth-spirit", 
                    "player_name": "Newbee.kaka", 
                    "gold": "4.1k", 
                    "kills": "-", 
                    "level": "9", 
                    "deaths": "3", 
                    "kda": "1.0", 
                    "lh": "18", 
                    "hh": "350", 
                    "assists": "3", 
                    "player_id": "/players/139876032", 
                    "td": "-", 
                    "xpm": "172", 
                    "hd": "1.2k"
                }
            ], 
            "team_id": "/esports/teams/4", 
            "team_name": "EHOME"
        }, 
        "dire": {
            "heroes": [
                {
                    "dn": "-", 
                    "gpm": "211", 
                    "lane": "Top (Safe)", 
                    "hero_name": "/heroes/pudge", 
                    "player_name": "VG.\u5929\u5594.Fy", 
                    "gold": "6.1k", 
                    "kills": "-", 
                    "level": "11", 
                    "deaths": "-", 
                    "kda": "6.0", 
                    "lh": "21", 
                    "hh": "317", 
                    "assists": "6", 
                    "player_id": "/players/101695162", 
                    "td": "-", 
                    "xpm": "275", 
                    "hd": "3k"
                }, 
                {
                    "dn": "2", 
                    "gpm": "229", 
                    "lane": "Dire Jungle", 
                    "hero_name": "/heroes/bane", 
                    "player_name": "EHOME.Fenrir", 
                    "gold": "6.6k", 
                    "kills": "3", 
                    "level": "11", 
                    "deaths": "4", 
                    "kda": "2.0", 
                    "lh": "22", 
                    "hh": "-", 
                    "assists": "5", 
                    "player_id": "/players/113800818", 
                    "td": "-", 
                    "xpm": "236", 
                    "hd": "2.6k"
                }, 
                {
                    "dn": "-", 
                    "gpm": "326", 
                    "lane": "Bottom (Off)", 
                    "hero_name": "/heroes/faceless-void", 
                    "player_name": "Wabisabi", 
                    "gold": "9.4k", 
                    "kills": "2", 
                    "level": "14", 
                    "deaths": "2", 
                    "kda": "4.0", 
                    "lh": "87", 
                    "hh": "658", 
                    "assists": "6", 
                    "player_id": "/players/100812084", 
                    "td": "333", 
                    "xpm": "385", 
                    "hd": "1.9k"
                }, 
                {
                    "dn": "6", 
                    "gpm": "481", 
                    "lane": "Middle", 
                    "hero_name": "/heroes/dragon-knight", 
                    "player_name": "CDEC.Super", 
                    "gold": "13.9k", 
                    "kills": "3", 
                    "level": "16", 
                    "deaths": "1", 
                    "kda": "11.0", 
                    "lh": "166", 
                    "hh": "90", 
                    "assists": "8", 
                    "player_id": "/players/90882159", 
                    "td": "1.5k", 
                    "xpm": "474", 
                    "hd": "7.4k"
                }, 
                {
                    "dn": "19", 
                    "gpm": "623", 
                    "lane": "Top (Safe)", 
                    "hero_name": "/heroes/gyrocopter", 
                    "player_name": "VG.BurNIng", 
                    "gold": "18k", 
                    "kills": "11", 
                    "level": "17", 
                    "deaths": "1", 
                    "kda": "16.0", 
                    "lh": "237", 
                    "hh": "-", 
                    "assists": "5", 
                    "player_id": "/players/90892734", 
                    "td": "1.8k", 
                    "xpm": "578", 
                    "hd": "12.1k"
                }
            ], 
            "team_id": "/esports/teams/726228", 
            "team_name": "Vici Gaming"
        }
    }
}